{
  "package-id": "hl7.fhir.uv.fhircast",
  "canonical": "http://hl7.org/fhir/uv/fhircast-docs",
  "title": "FHIRCast Implementation Guide",
  "introduction": "FHIRcast synchronizes healthcare applications in real time to show the same clinical content to a common user.",
  "list": [
    {
      "version": "STU3",
      "path": "'http://hl7.org/fhir/uv/fhircast-docs",
      "desc": "Continuous Integration Build (latest in version control)",
      "sequence": "STU3",
      "fhirversion": "4.0.1",
      "status": "ballot",
      "current": true,
      "date": "2022-03-24"
    }
  ],
  "category": "Exchange"
}
